goat_quantumcontrol/__init__.py
goat_quantumcontrol/log.py
goat_quantumcontrol/optimization.py
goat_quantumcontrol/pulses.py
goat_quantumcontrol-0.0.6.dist-info/LICENSE
goat_quantumcontrol-0.0.6.dist-info/METADATA
goat_quantumcontrol-0.0.6.dist-info/WHEEL
goat_quantumcontrol-0.0.6.dist-info/top_level.txt
goat_quantumcontrol-0.0.6.dist-info/RECORD
