Metadata-Version: 2.1
Name: goat-quantumcontrol
Version: 0.0.6
Summary: Python implementation of the quantum optimal control GOAT-algorithm
Home-page: https://github.com/pmarkus-github/goat-quantumcontrol
Author: Markus Plautz
Author-email: <markus.plautz@gmx.at>
License: UNKNOWN
Keywords: python,quantum-control,goat,quantum-gates,quantum-computer
Platform: UNKNOWN
Classifier: Development Status :: 4 - Beta
Classifier: Intended Audience :: Science/Research
Classifier: Programming Language :: Python :: 3
Classifier: Operating System :: Unix
Classifier: Operating System :: MacOS :: MacOS X
Classifier: Operating System :: Microsoft :: Windows
License-File: LICENSE
Requires-Dist: numpy
Requires-Dist: scipy
Requires-Dist: matplotlib
